CHANGELOG.rst
MANIFEST.in
README.md
README.rst
setup.cfg
setup.py
./kipartbase/__init__.py
./kipartbase/__main__.py
./kipartbase/manage.py
./kipartbase/api/__init__.py
./kipartbase/api/admin.py
./kipartbase/api/apps.py
./kipartbase/api/file_storage.py
./kipartbase/api/models.py
./kipartbase/api/tests.py
./kipartbase/api/versioned_file_storage.py
./kipartbase/api/migrations/0001_initial.py
./kipartbase/api/migrations/0002_initial_data.py
./kipartbase/api/migrations/0003_auto_20170602_1025.py
./kipartbase/api/migrations/0004_auto_20170602_1454.py
./kipartbase/api/migrations/0005_remove_partdistributor_package_price.py
./kipartbase/api/migrations/0006_auto_20170605_0944.py
./kipartbase/api/migrations/0007_auto_20170605_1218.py
./kipartbase/api/migrations/0008_auto_20170605_1220.py
./kipartbase/api/migrations/0009_auto_20170605_2131.py
./kipartbase/api/migrations/0010_footprint_image.py
./kipartbase/api/migrations/0011_auto_20170611_1428.py
./kipartbase/api/migrations/0012_auto_20170612_0857.py
./kipartbase/api/migrations/0013_auto_20170612_0921.py
./kipartbase/api/migrations/0014_auto_20170612_0923.py
./kipartbase/api/migrations/0015_auto_20170614_1229.py
./kipartbase/api/migrations/0016_footprint_snapeda.py
./kipartbase/api/migrations/0017_auto_20170627_0846.py
./kipartbase/api/migrations/0018_partdistributor_quantity.py
./kipartbase/api/migrations/0019_auto_20170708_0939.py
./kipartbase/api/migrations/0020_auto_20170708_0947.py
./kipartbase/api/migrations/0021_auto_20170709_2250.py
./kipartbase/api/migrations/0022_auto_20170709_2338.py
./kipartbase/api/migrations/0023_auto_20170710_0935.py
./kipartbase/api/migrations/0024_partoffer_updated.py
./kipartbase/api/migrations/0025_auto_20170712_0908.py
./kipartbase/api/migrations/0026_partstockhistory.py
./kipartbase/api/migrations/0027_auto_20170718_2149.py
./kipartbase/api/migrations/0028_auto_20170720_1024.py
./kipartbase/api/migrations/0029_auto_20170720_1319.py
./kipartbase/api/migrations/0030_auto_20170721_1004.py
kipartman.egg-info/PKG-INFO
kipartman.egg-info/SOURCES.txt
kipartman.egg-info/dependency_links.txt
kipartman.egg-info/entry_points.txt
kipartman.egg-info/requires.txt
kipartman.egg-info/top_level.txt
