Metadata-Version: 1.0
Name: kipartman
Version: 0.6.0
Summary: Kicad part manager
Home-page: https://github.com/turdusmerula/kipartman/
Author: Sebastien Besombes
Author-email: UNKNOWN
License: GPLv3
Platform: UNKNOWN
